UsfMsds501JisuanShujuKexueZhongwenJiangyi/README.md
UsfMsds501JisuanShujuKexueZhongwenJiangyi/__init__.py
UsfMsds501JisuanShujuKexueZhongwenJiangyi/__main__.py
UsfMsds501JisuanShujuKexueZhongwenJiangyi/file.epub
UsfMsds501JisuanShujuKexueZhongwenJiangyi/index.html
UsfMsds501JisuanShujuKexueZhongwenJiangyi/css/__init__.py
UsfMsds501JisuanShujuKexueZhongwenJiangyi/css/annotations.css
UsfMsds501JisuanShujuKexueZhongwenJiangyi/css/main.css
UsfMsds501JisuanShujuKexueZhongwenJiangyi/css/normalize.css
UsfMsds501JisuanShujuKexueZhongwenJiangyi/css/popup.css
UsfMsds501JisuanShujuKexueZhongwenJiangyi/font/__init__.py
UsfMsds501JisuanShujuKexueZhongwenJiangyi/font/fontello.eot
UsfMsds501JisuanShujuKexueZhongwenJiangyi/font/fontello.svg
UsfMsds501JisuanShujuKexueZhongwenJiangyi/font/fontello.ttf
UsfMsds501JisuanShujuKexueZhongwenJiangyi/font/fontello.woff
UsfMsds501JisuanShujuKexueZhongwenJiangyi/img/__init__.py
UsfMsds501JisuanShujuKexueZhongwenJiangyi/img/annotator-glyph-sprite.png
UsfMsds501JisuanShujuKexueZhongwenJiangyi/img/annotator-icon-sprite.png
UsfMsds501JisuanShujuKexueZhongwenJiangyi/img/apple-touch-icon.png
UsfMsds501JisuanShujuKexueZhongwenJiangyi/img/cancelfullscreen.png
UsfMsds501JisuanShujuKexueZhongwenJiangyi/img/close.png
UsfMsds501JisuanShujuKexueZhongwenJiangyi/img/fullscreen.png
UsfMsds501JisuanShujuKexueZhongwenJiangyi/img/loader.gif
UsfMsds501JisuanShujuKexueZhongwenJiangyi/img/menu-icon.png
UsfMsds501JisuanShujuKexueZhongwenJiangyi/img/save.png
UsfMsds501JisuanShujuKexueZhongwenJiangyi/img/saved.png
UsfMsds501JisuanShujuKexueZhongwenJiangyi/img/settings-s.png
UsfMsds501JisuanShujuKexueZhongwenJiangyi/img/settings.png
UsfMsds501JisuanShujuKexueZhongwenJiangyi/img/star.png
UsfMsds501JisuanShujuKexueZhongwenJiangyi/js/__init__.py
UsfMsds501JisuanShujuKexueZhongwenJiangyi/js/epub.js
UsfMsds501JisuanShujuKexueZhongwenJiangyi/js/epub.min.js
UsfMsds501JisuanShujuKexueZhongwenJiangyi/js/epub.min.map
UsfMsds501JisuanShujuKexueZhongwenJiangyi/js/hooks.min.js
usf_msds501_jisuan_shuju_kexue_zhongwen_jiangyi-2024.3.5.0.dist-info/METADATA
usf_msds501_jisuan_shuju_kexue_zhongwen_jiangyi-2024.3.5.0.dist-info/WHEEL
usf_msds501_jisuan_shuju_kexue_zhongwen_jiangyi-2024.3.5.0.dist-info/entry_points.txt
usf_msds501_jisuan_shuju_kexue_zhongwen_jiangyi-2024.3.5.0.dist-info/top_level.txt
usf_msds501_jisuan_shuju_kexue_zhongwen_jiangyi-2024.3.5.0.dist-info/RECORD
